ccrp/__init__.py
ccrp/commands.py
ccrp/hacky.py
ccrp/usb.py
ccrp/utils.py
ccrp/version
ccrp/version.py
ccrp-0.0.2.dist-info/METADATA
ccrp-0.0.2.dist-info/WHEEL
ccrp-0.0.2.dist-info/top_level.txt
ccrp-0.0.2.dist-info/RECORD
