Metadata-Version: 2.1
Name: ccrp
Version: 0.0.2
Summary: Python library for cheap receipt printers
Home-page: https://github.com/aapeliv/ccrp
Author: Aapeli Vuorinen
Classifier: License :: OSI Approved :: MIT License
Requires-Python: >=3.9
Requires-Dist: pyusb
